jax_util/__init__.py
jax_util-0.2.0.dist-info/LICENSE
jax_util-0.2.0.dist-info/WHEEL
jax_util-0.2.0.dist-info/METADATA
jax_util-0.2.0.dist-info/RECORD
