Metadata-Version: 2.1
Name: jax-util
Version: 0.2.0
Summary: jax/_src/util.py extracted as a standalone Python library
Home-page: https://github.com/shawwn/jax-util
License: MIT
Author: Shawn Presser
Requires-Python: >=3.6,<4.0
Classifier: License :: OSI Approved :: MIT License
Classifier: Programming Language :: Python :: 3
Classifier: Programming Language :: Python :: 3.6
Classifier: Programming Language :: Python :: 3.7
Classifier: Programming Language :: Python :: 3.8
Classifier: Programming Language :: Python :: 3.9
Project-URL: @theshawwn on Twitter, https://www.twitter.com/theshawwn
Project-URL: Shawn's Website, https://www.shawwn.com
Project-URL: Support me on Patreon, https://www.patreon.com/shawwn
Project-URL: sillysaurusx on Hacker News, https://news.ycombinator.com/threads?id=sillysaurusx
